instantauth/coders
instantauth
instantauth/verifiers
instantauth/cryptors
