Metadata-Version: 1.0
Name: instantauth
Version: 0.8.5
Summary: Not very credential authentication model.
Home-page: https://github.com/youknowone/instantauth
Author: Jeong YunWon
Author-email: jeong+instantauth@youknowone.org
License: UNKNOWN
Platform: UNKNOWN
